odoo/addons/partner_tag_smart_assignation/README.rst
odoo/addons/partner_tag_smart_assignation/__init__.py
odoo/addons/partner_tag_smart_assignation/__manifest__.py
odoo/addons/partner_tag_smart_assignation/cron/update_cron.xml
odoo/addons/partner_tag_smart_assignation/i18n/partner_tag_smart_assignation.pot
odoo/addons/partner_tag_smart_assignation/migrations/11.0.1.0.0/pre-migration.py
odoo/addons/partner_tag_smart_assignation/models/__init__.py
odoo/addons/partner_tag_smart_assignation/models/res_partner_category.py
odoo/addons/partner_tag_smart_assignation/readme/CONTRIBUTORS.rst
odoo/addons/partner_tag_smart_assignation/readme/DESCRIPTION.rst
odoo/addons/partner_tag_smart_assignation/static/description/icon.png
odoo/addons/partner_tag_smart_assignation/static/description/index.html
odoo/addons/partner_tag_smart_assignation/tests/__init__.py
odoo/addons/partner_tag_smart_assignation/tests/test_smart_tagger.py
odoo/addons/partner_tag_smart_assignation/views/smart_tagger_view.xml
odoo11_addon_partner_tag_smart_assignation-11.0.1.1.0.dist-info/METADATA
odoo11_addon_partner_tag_smart_assignation-11.0.1.1.0.dist-info/WHEEL
odoo11_addon_partner_tag_smart_assignation-11.0.1.1.0.dist-info/top_level.txt
odoo11_addon_partner_tag_smart_assignation-11.0.1.1.0.dist-info/RECORD
